nglstrike/__init__.py
nglstrike/__main__.py
nglstrike/main.py
nglstrike-1.3.0.dist-info/licenses/LICENSE
nglstrike-1.3.0.dist-info/METADATA
nglstrike-1.3.0.dist-info/WHEEL
nglstrike-1.3.0.dist-info/entry_points.txt
nglstrike-1.3.0.dist-info/top_level.txt
nglstrike-1.3.0.dist-info/RECORD
