Metadata-Version: 2.4
Name: nglstrike
Version: 1.3.0
Summary: Anonymous Auto-Sender for NGL
Author: Mallik Mohammed Musaddiq
Author-email: Mallik Mohammed Musaddiq <mallikmusaddiq1@gmail.com>
License: MIT
Project-URL: Homepage, https://github.com/mallikmusaddiq1/nglstrike
Requires-Python: >=3.6
License-File: LICENSE
Requires-Dist: requests
Dynamic: author
Dynamic: license-file
Dynamic: requires-python
